{
  "$schema": "https://biomejs.dev/schemas/1.9.4/schema.json",
  "formatter": {
    "enabled": true,
    "ignore": ["dist/**"],
    "indentStyle": "space",
    "lineWidth": 100
  },
  "linter": {
    "enabled": true,
    "ignore": ["dist/**"],
    "rules": {
      "a11y": {
        "noSvgWithoutTitle": "off"
      },
      "complexity": {
        "noUselessStringConcat": "error",
        "noUselessUndefinedInitialization": "error",
        "useDateNow": "error",
        "useLiteralKeys": "off"
      },
      "correctness": {
        "noConstantMathMinMaxClamp": "error",
        "noUndeclaredDependencies": "error",
        "noUnusedImports": "error",
        "useArrayLiterals": "error",
        "useHookAtTopLevel": "error",
        "useImportExtensions": "error"
      },
      "nursery": {
        "noCommonJs": "error",
        "noEnum": "error",
        "noSubstr": "error",
        "noTemplateCurlyInString": "error",
        "useAdjacentOverloadSignatures": "error",
        "useCollapsedIf": "error",
        "useConsistentCurlyBraces": "error",
        "useSortedClasses": { "fix": "safe", "level": "error", "options": { "functions": ["tw"] } },
        "useTrimStartEnd": "error"
      },
      "performance": {
        "noBarrelFile": "error",
        "noReExportAll": "error"
      },
      "recommended": true,
      "style": {
        "noDoneCallback": "error",
        "noDefaultExport": "error",
        "noImplicitBoolean": "error",
        "noNamespace": "error",
        "noNamespaceImport": "error",
        "noNegationElse": "error",
        "noYodaExpression": "error",
        "useBlockStatements": "error",
        "useCollapsedElseIf": "error",
        "useConsistentArrayType": { "level": "error", "options": { "syntax": "shorthand" } },
        "useConsistentBuiltinInstantiation": "error",
        "useExplicitLengthCheck": "error",
        "useFilenamingConvention": {
          "level": "error",
          "options": { "filenameCases": ["kebab-case"], "requireAscii": true }
        },
        "useForOf": "error",
        "useFragmentSyntax": "error",
        "useNodeAssertStrict": "error",
        "useShorthandArrayType": "error",
        "useShorthandAssign": "error",
        "useSingleCaseStatement": "error",
        "useThrowOnlyError": "error"
      },
      "suspicious": {
        "noConfusingVoidType": "off",
        "noMisplacedAssertion": "error",
        "useAwait": "error",
        "useErrorMessage": "error",
        "useNumberToFixedDigitsArgument": "error"
      }
    }
  },
  "organizeImports": {
    "enabled": true,
    "ignore": ["dist/**"]
  }
}
